{
  "version": "2026.07",
  "sectorVisionWeights": {
    "تقنية المعلومات": 88,
    "الصناعة والتصنيع": 86,
    "الطاقة المتجددة": 94,
    "السياحة والترفيه": 86,
    "الخدمات اللوجستية": 84,
    "التجارة والتجزئة": 68,
    "العقارات والمقاولات": 64,
    "الرعاية الصحية": 84,
    "التعليم": 78,
    "الزراعة والأغذية": 76,
    "أخرى": 62
  },
  "benchmarks": {
    "تقنية المعلومات": { "liquidityRatio": 2.1, "debtRatio": 0.35, "profitMargin": 0.18 },
    "الصناعة والتصنيع": { "liquidityRatio": 1.4, "debtRatio": 0.5, "profitMargin": 0.1 },
    "الطاقة المتجددة": { "liquidityRatio": 1.6, "debtRatio": 0.55, "profitMargin": 0.12 },
    "السياحة والترفيه": { "liquidityRatio": 1.3, "debtRatio": 0.45, "profitMargin": 0.09 },
    "الخدمات اللوجستية": { "liquidityRatio": 1.5, "debtRatio": 0.48, "profitMargin": 0.08 },
    "التجارة والتجزئة": { "liquidityRatio": 1.2, "debtRatio": 0.5, "profitMargin": 0.07 },
    "العقارات والمقاولات": { "liquidityRatio": 1.1, "debtRatio": 0.6, "profitMargin": 0.11 },
    "الرعاية الصحية": { "liquidityRatio": 1.8, "debtRatio": 0.4, "profitMargin": 0.14 },
    "التعليم": { "liquidityRatio": 1.7, "debtRatio": 0.3, "profitMargin": 0.12 },
    "الزراعة والأغذية": { "liquidityRatio": 1.4, "debtRatio": 0.42, "profitMargin": 0.09 },
    "أخرى": { "liquidityRatio": 1.5, "debtRatio": 0.45, "profitMargin": 0.1 }
  }
}
